{
    "adsrvr.org": {
        "/": {
            "TDID": {
                "name": "TDID",
                "domain": ".adsrvr.org",
                "path": "/",
                "current_label": 3,
                "label_ts": 1728577763133,
                "storeId": "1",
                "variable_data": [
                    {
                        "host_only": false,
                        "http_only": false,
                        "secure": true,
                        "session": false,
                        "expirationDate": 1760113763.131979,
                        "expiry": 31536000.13197899,
                        "value": "f35508a1-9c21-4362-bab0-733beea1a5d8",
                        "same_site": "no_restriction",
                        "timestamp": 1728577763132
                    }
                ]
            }
        }
    },
    "crwdcntrl.net": {
        "/": {
            "_cc_cc": {
                "name": "_cc_cc",
                "domain": ".crwdcntrl.net",
                "path": "/",
                "current_label": 3,
                "label_ts": 1728577764806,
                "storeId": "1",
                "variable_data": [
                    {
                        "host_only": false,
                        "http_only": false,
                        "secure": true,
                        "session": true,
                        "expiry": 0,
                        "value": "ctst",
                        "same_site": "no_restriction",
                        "timestamp": 1728577764805
                    }
                ]
            },
            "_cc_dc": {
                "name": "_cc_dc",
                "domain": ".crwdcntrl.net",
                "path": "/",
                "current_label": 3,
                "label_ts": 1728577764952,
                "storeId": "1",
                "variable_data": [
                    {
                        "host_only": false,
                        "http_only": false,
                        "secure": true,
                        "session": false,
                        "expirationDate": 1751904419.951032,
                        "expiry": 23326655.951031923,
                        "value": "0",
                        "same_site": "no_restriction",
                        "timestamp": 1728577764951
                    }
                ]
            },
            "_cc_id": {
                "name": "_cc_id",
                "domain": ".crwdcntrl.net",
                "path": "/",
                "current_label": 3,
                "label_ts": 1728577764953,
                "storeId": "1",
                "variable_data": [
                    {
                        "host_only": false,
                        "http_only": false,
                        "secure": true,
                        "session": false,
                        "expirationDate": 1751904419.951102,
                        "expiry": 23326655.95110202,
                        "value": "cb77f693e1fb176414cf98c838f18350",
                        "same_site": "no_restriction",
                        "timestamp": 1728577764952
                    }
                ]
            }
        }
    },
    "demdex.net": {
        "/": {
            "demdex": {
                "name": "demdex",
                "domain": ".demdex.net",
                "path": "/",
                "current_label": 3,
                "label_ts": 1728577763250,
                "storeId": "1",
                "variable_data": [
                    {
                        "host_only": false,
                        "http_only": false,
                        "secure": true,
                        "session": false,
                        "expirationDate": 1744129763.249123,
                        "expiry": 15552000.249123096,
                        "value": "81456487842193936454111442745510522151",
                        "same_site": "no_restriction",
                        "timestamp": 1728577763249
                    },
                    {
                        "host_only": false,
                        "http_only": false,
                        "secure": true,
                        "session": false,
                        "expiry": 15552000.088903904,
                        "value": "81456487842193936454111442745510522151",
                        "same_site": "no_restriction",
                        "timestamp": 1728577764091
                    },
                    {
                        "host_only": false,
                        "http_only": false,
                        "secure": true,
                        "session": false,
                        "expiry": 15552000.369014978,
                        "value": "81456487842193936454111442745510522151",
                        "same_site": "no_restriction",
                        "timestamp": 1728577774370
                    }
                ]
            }
        }
    },
    "doubleclick.net": {
        "/": {
            "IDE": {
                "name": "IDE",
                "domain": ".doubleclick.net",
                "path": "/",
                "current_label": 3,
                "label_ts": 1728577763703,
                "storeId": "1",
                "variable_data": [
                    {
                        "host_only": false,
                        "http_only": true,
                        "secure": true,
                        "session": false,
                        "expirationDate": 1763137763.702015,
                        "expiry": 34560000.70201492,
                        "value": "AHWqTUmKOIj4sKtE5eaJbYoCMgGzHKaB_vhKMrnEt0pdnR9dHO_bpztpXXoAhCAfK9M",
                        "same_site": "no_restriction",
                        "timestamp": 1728577763702
                    },
                    {
                        "host_only": false,
                        "http_only": true,
                        "secure": true,
                        "session": false,
                        "expiry": 34560000.814973116,
                        "value": "AHWqTUnraW0ARPfUKQOSAn61nqxCeZgH8X_Nmqlc0lvWkZ2OH80sF3aMAs6Er9NfqGc",
                        "same_site": "no_restriction",
                        "timestamp": 1728577763818
                    },
                    {
                        "host_only": false,
                        "http_only": true,
                        "secure": true,
                        "session": false,
                        "expiry": 34560000.8155489,
                        "value": "AHWqTUnMFtYaLVlLBf5RmEN9LftmcGoFXEKhhTbdfIu2J6NZf8yke-Vb6nFXz-doXJg",
                        "same_site": "no_restriction",
                        "timestamp": 1728577763820
                    }
                ]
            },
            "ar_debug": {
                "name": "ar_debug",
                "domain": ".doubleclick.net",
                "path": "/",
                "current_label": 0,
                "label_ts": 1728577763498,
                "storeId": "1",
                "variable_data": [
                    {
                        "host_only": false,
                        "http_only": true,
                        "secure": true,
                        "session": false,
                        "expirationDate": 1731169763.49249,
                        "expiry": 2592000.492490053,
                        "value": "1",
                        "same_site": "no_restriction",
                        "timestamp": 1728577763497
                    }
                ]
            },
            "receive-cookie-deprecation": {
                "name": "receive-cookie-deprecation",
                "domain": ".doubleclick.net",
                "path": "/",
                "current_label": 3,
                "label_ts": 1728577763704,
                "storeId": "1",
                "variable_data": [
                    {
                        "host_only": false,
                        "http_only": true,
                        "secure": true,
                        "session": false,
                        "expirationDate": 1744129763.702104,
                        "expiry": 15552000.702104092,
                        "value": "1",
                        "same_site": "no_restriction",
                        "timestamp": 1728577763704
                    },
                    {
                        "host_only": false,
                        "http_only": true,
                        "secure": true,
                        "session": false,
                        "expiry": 15552000.815098047,
                        "value": "1",
                        "same_site": "no_restriction",
                        "timestamp": 1728577763818
                    },
                    {
                        "host_only": false,
                        "http_only": true,
                        "secure": true,
                        "session": false,
                        "expiry": 15552000.815741062,
                        "value": "1",
                        "same_site": "no_restriction",
                        "timestamp": 1728577763820
                    }
                ]
            },
            "test_cookie": {
                "name": "test_cookie",
                "domain": ".doubleclick.net",
                "path": "/",
                "current_label": 3,
                "label_ts": 1728577763201,
                "storeId": "1",
                "variable_data": [
                    {
                        "host_only": false,
                        "http_only": true,
                        "secure": true,
                        "session": false,
                        "expirationDate": 1728578663.199236,
                        "expiry": 900.1992359161377,
                        "value": "CheckForPermission",
                        "same_site": "no_restriction",
                        "timestamp": 1728577763199
                    },
                    {
                        "host_only": false,
                        "http_only": false,
                        "secure": true,
                        "session": false,
                        "expiry": 900.4852879047394,
                        "value": "CheckForPermission",
                        "same_site": "no_restriction",
                        "timestamp": 1728577763489
                    },
                    {
                        "host_only": false,
                        "http_only": true,
                        "secure": true,
                        "session": false,
                        "expiry": 900.4870760440826,
                        "value": "CheckForPermission",
                        "same_site": "no_restriction",
                        "timestamp": 1728577763491
                    },
                    {
                        "host_only": false,
                        "http_only": false,
                        "secure": true,
                        "session": false,
                        "expiry": 900.4925570487976,
                        "value": "CheckForPermission",
                        "same_site": "no_restriction",
                        "timestamp": 1728577763498
                    },
                    {
                        "host_only": false,
                        "http_only": true,
                        "secure": true,
                        "session": false,
                        "expiry": 900.5024800300598,
                        "value": "CheckForPermission",
                        "same_site": "no_restriction",
                        "timestamp": 1728577763505
                    },
                    {
                        "host_only": false,
                        "http_only": false,
                        "secure": true,
                        "session": false,
                        "expiry": 900.5604979991913,
                        "value": "CheckForPermission",
                        "same_site": "no_restriction",
                        "timestamp": 1728577763561
                    }
                ]
            }
        }
    },
    "dpm.demdex.net": {
        "/": {
            "dpm": {
                "name": "dpm",
                "domain": ".dpm.demdex.net",
                "path": "/",
                "current_label": 3,
                "label_ts": 1728577764090,
                "storeId": "1",
                "variable_data": [
                    {
                        "host_only": false,
                        "http_only": false,
                        "secure": true,
                        "session": false,
                        "expirationDate": 1744129764.088869,
                        "expiry": 15552000.088869095,
                        "value": "81456487842193936454111442745510522151",
                        "same_site": "no_restriction",
                        "timestamp": 1728577764089
                    }
                ]
            }
        }
    },
    "everesttech.net": {
        "/": {
            "everest_g_v2": {
                "name": "everest_g_v2",
                "domain": ".everesttech.net",
                "path": "/",
                "current_label": 0,
                "label_ts": 1728577763950,
                "storeId": "1",
                "variable_data": [
                    {
                        "host_only": false,
                        "http_only": false,
                        "secure": true,
                        "session": false,
                        "expirationDate": 1760113763.94902,
                        "expiry": 31536000.94901991,
                        "value": "g_surferid~ZwgA5AAAAF0B3ANP",
                        "same_site": "no_restriction",
                        "timestamp": 1728577763949
                    }
                ]
            }
        }
    },
    "geoip.radio-canada.ca": {
        "/": {
            "ARRAffinity": {
                "name": "ARRAffinity",
                "domain": ".geoip.radio-canada.ca",
                "path": "/",
                "current_label": 0,
                "label_ts": 1728577762073,
                "storeId": "1",
                "variable_data": [
                    {
                        "host_only": false,
                        "http_only": true,
                        "secure": true,
                        "session": true,
                        "expiry": 0,
                        "value": "b51368e22d246c77acab78ced4658e792d3d55bb527a12870a9497b6721e1be2",
                        "same_site": "unspecified",
                        "timestamp": 1728577762072
                    }
                ]
            },
            "ARRAffinitySameSite": {
                "name": "ARRAffinitySameSite",
                "domain": ".geoip.radio-canada.ca",
                "path": "/",
                "current_label": 0,
                "label_ts": 1728577762074,
                "storeId": "1",
                "variable_data": [
                    {
                        "host_only": false,
                        "http_only": true,
                        "secure": true,
                        "session": true,
                        "expiry": 0,
                        "value": "b51368e22d246c77acab78ced4658e792d3d55bb527a12870a9497b6721e1be2",
                        "same_site": "no_restriction",
                        "timestamp": 1728577762073
                    }
                ]
            }
        }
    },
    "google.com": {
        "/": {
            "NID": {
                "name": "NID",
                "domain": ".google.com",
                "path": "/",
                "current_label": 0,
                "label_ts": 1728577768457,
                "storeId": "1",
                "variable_data": [
                    {
                        "host_only": false,
                        "http_only": true,
                        "secure": true,
                        "session": false,
                        "expirationDate": 1744388968.455879,
                        "expiry": 15811200.455878973,
                        "value": "518=u2BSuu9tTQgoUhfS_kByXLcxVRmc3uUcRaqXT8fIDne4WibleeLldrFEiLTl0rfKhK1gFy0Hl1Pft4Pfo1qoo7eq9scEj0J6PHs8E3MH5dCVlQw-3F-7__4eVRW7wzFeeeCEmTntkK82ZmrkqPoc0Dllks29ctK45nGPLWXMxtGqH8LSwQ",
                        "same_site": "no_restriction",
                        "timestamp": 1728577768456
                    },
                    {
                        "host_only": false,
                        "http_only": true,
                        "secure": true,
                        "session": false,
                        "expiry": 15811187.923857927,
                        "value": "518=Dpbf8FqsKA1mDo5XE3TE5RyyWRnJSpM6hfIBDJLglvJjWvhujqbm7AxVSujfFyJf67slD-yni0eXniztcKOwfqbbjrxyGD8Je_gXSxmzakVT_Lht-foFQn38D94kJ07AoRkSs6n43A_QltsKMywWA8PnfEJADo8ezSvJXEu15UkvLXL3kdb_iqvljpVY0SqmGj54_mAgp0vCoA3JMx6kPJqt4-5NktT4RIwXmfDfVhalvwx3VGt_4Q",
                        "same_site": "no_restriction",
                        "timestamp": 1728577780928
                    },
                    {
                        "host_only": false,
                        "http_only": true,
                        "secure": true,
                        "session": false,
                        "expiry": 15811200.605211973,
                        "value": "518=0ct7GfFQW0SuRY-11spEiKONntzQHVxIaA8CKStcDrOOQ3yQmZNncCzCBXCVwGixwniEXf1feZPku42p5EMeJCHbwIiDbZhYEq8N7WrJqp8PWgmDaep1J-PqzReDLpDrw6IJjoAfmdRubnQiuCH27mpPYcyPHDR_ZcV-CuUpIO-St4zAHaMDXWWOXQfGLZYbdLMPlwniYyILRM6idPZo3R3Z7wCNAgyRw00s0k_KPa4RhVfSyAfr-3MLJhIwUA",
                        "same_site": "no_restriction",
                        "timestamp": 1728577781606
                    },
                    {
                        "host_only": false,
                        "http_only": true,
                        "secure": true,
                        "session": false,
                        "expiry": 15811200.75251007,
                        "value": "518=EQyXpzNrOXv5-Ufljz-dn8x1mhgOwNEVYSmyBRDObe_C_9qHZx2qL4imgnsGGAZxm2676aNSxuZ9VZEmudhmK5JSJr0MQnMyI938v5MAOjsaez3E7uMPo-JJ840aYfIlDy1gygbaPDypJHhFGNXDupIdv-r-Dte0qb4EQHSiHgIViVsb0efVfLorZMmvXTkituZ4Fz6zqTb9a6twuYXd7y_Dnj-8MqYxfmn7mAJLc3TnijffW_1HJ_dVWaF5RQ",
                        "same_site": "no_restriction",
                        "timestamp": 1728577781753
                    }
                ]
            }
        }
    },
    "ici.radio-canada.ca": {
        "/": {
            "_awl": {
                "name": "_awl",
                "domain": ".ici.radio-canada.ca",
                "path": "/",
                "current_label": 3,
                "label_ts": 1728577763493,
                "storeId": "1",
                "variable_data": [
                    {
                        "host_only": false,
                        "http_only": false,
                        "secure": true,
                        "session": false,
                        "expirationDate": 1762705763.485,
                        "expiry": 34128000.484999895,
                        "value": "3.1728577763.5-52e06d70b910db1fbf6bd1f7cd42948a-6763652d75732d63656e7472616c31-0",
                        "same_site": "no_restriction",
                        "timestamp": 1728577763491
                    }
                ]
            },
            "BCSessionID": {
                "name": "BCSessionID",
                "domain": "ici.radio-canada.ca",
                "path": "/",
                "current_label": 0,
                "label_ts": 1728577764259,
                "storeId": "1",
                "variable_data": [
                    {
                        "host_only": true,
                        "http_only": false,
                        "secure": true,
                        "session": true,
                        "expiry": 0,
                        "value": "f27fd1f1-4baf-463f-a312-1c5bf8cca7b0",
                        "same_site": "unspecified",
                        "timestamp": 1728577764258
                    }
                ]
            },
            "BCTempID": {
                "name": "BCTempID",
                "domain": "ici.radio-canada.ca",
                "path": "/",
                "current_label": 0,
                "label_ts": 1728577763893,
                "storeId": "1",
                "variable_data": [
                    {
                        "host_only": true,
                        "http_only": false,
                        "secure": true,
                        "session": false,
                        "expirationDate": 1728578363,
                        "expiry": 600,
                        "value": "f27fd1f1-4baf-463f-a312-1c5bf8cca7b0",
                        "same_site": "unspecified",
                        "timestamp": 1728577763892
                    }
                ]
            },
            "RCF1": {
                "name": "RCF1",
                "domain": "ici.radio-canada.ca",
                "path": "/",
                "current_label": 1,
                "label_ts": 1728577761919,
                "storeId": "1",
                "variable_data": [
                    {
                        "host_only": true,
                        "http_only": false,
                        "secure": false,
                        "session": true,
                        "expiry": 0,
                        "value": "1",
                        "same_site": "unspecified",
                        "timestamp": 1728577761918
                    }
                ]
            },
            "last_visit_bc": {
                "name": "last_visit_bc",
                "domain": "ici.radio-canada.ca",
                "path": "/",
                "current_label": 2,
                "label_ts": 1728577763230,
                "storeId": "1",
                "variable_data": [
                    {
                        "host_only": true,
                        "http_only": false,
                        "secure": true,
                        "session": false,
                        "expirationDate": 1760113763,
                        "expiry": 31536000,
                        "value": "1728577763229",
                        "same_site": "unspecified",
                        "timestamp": 1728577763229
                    }
                ]
            }
        }
    },
    "linkedin.com": {
        "/": {
            "AnalyticsSyncHistory": {
                "name": "AnalyticsSyncHistory",
                "domain": ".linkedin.com",
                "path": "/",
                "current_label": 2,
                "label_ts": 1728577775965,
                "storeId": "1",
                "variable_data": [
                    {
                        "host_only": false,
                        "http_only": false,
                        "secure": true,
                        "session": false,
                        "expirationDate": 1731169775.963021,
                        "expiry": 2592000.96302104,
                        "value": "AQL32BWmbGfuRAAAAZJ3Q6omG_8_dT2ZzjSyURyztrB4PPskU7PXb2_JbEvoMvlbSt7MTwK8yfJH1lI3lBHvog",
                        "same_site": "no_restriction",
                        "timestamp": 1728577775965
                    }
                ]
            },
            "UserMatchHistory": {
                "name": "UserMatchHistory",
                "domain": ".linkedin.com",
                "path": "/",
                "current_label": 3,
                "label_ts": 1728577775965,
                "storeId": "1",
                "variable_data": [
                    {
                        "host_only": false,
                        "http_only": false,
                        "secure": true,
                        "session": false,
                        "expirationDate": 1731169775.963005,
                        "expiry": 2592000.963005066,
                        "value": "AQJpryAkTbqUMwAAAZJ3Q6omWd_EZ0Cw5HjKZgrmVjDGmISLdtjRqYQ8wDXz0WOzmGw5VZ0hZ4EjiA",
                        "same_site": "no_restriction",
                        "timestamp": 1728577775964
                    }
                ]
            },
            "bcookie": {
                "name": "bcookie",
                "domain": ".linkedin.com",
                "path": "/",
                "current_label": 0,
                "label_ts": 1728577775788,
                "storeId": "1",
                "variable_data": [
                    {
                        "host_only": false,
                        "http_only": false,
                        "secure": true,
                        "session": false,
                        "expirationDate": 1760113775.786485,
                        "expiry": 31536000.786484957,
                        "value": "\"v=2&cdddfe58-f52f-4f3a-8b69-3d0b072c1b5d\"",
                        "same_site": "no_restriction",
                        "timestamp": 1728577775788
                    },
                    {
                        "host_only": false,
                        "http_only": false,
                        "secure": true,
                        "session": false,
                        "expiry": 31536001.96303606,
                        "value": "\"v=2&cdddfe58-f52f-4f3a-8b69-3d0b072c1b5d\"",
                        "same_site": "no_restriction",
                        "timestamp": 1728577775965
                    },
                    {
                        "host_only": false,
                        "http_only": false,
                        "secure": true,
                        "session": false,
                        "expiry": 31536001.442049026,
                        "value": "\"v=2&cdddfe58-f52f-4f3a-8b69-3d0b072c1b5d\"",
                        "same_site": "no_restriction",
                        "timestamp": 1728577776444
                    }
                ]
            },
            "li_sugr": {
                "name": "li_sugr",
                "domain": ".linkedin.com",
                "path": "/",
                "current_label": 3,
                "label_ts": 1728577775787,
                "storeId": "1",
                "variable_data": [
                    {
                        "host_only": false,
                        "http_only": false,
                        "secure": true,
                        "session": false,
                        "expirationDate": 1736353775.786449,
                        "expiry": 7776000.786448956,
                        "value": "78a1da6a-438c-4498-9e09-f3c636d6d699",
                        "same_site": "no_restriction",
                        "timestamp": 1728577775787
                    },
                    {
                        "host_only": false,
                        "http_only": false,
                        "secure": true,
                        "session": false,
                        "expiry": 7776000.962949991,
                        "value": "78a1da6a-438c-4498-9e09-f3c636d6d699",
                        "same_site": "no_restriction",
                        "timestamp": 1728577775963
                    },
                    {
                        "host_only": false,
                        "http_only": false,
                        "secure": true,
                        "session": false,
                        "expiry": 7776000.441972017,
                        "value": "78a1da6a-438c-4498-9e09-f3c636d6d699",
                        "same_site": "no_restriction",
                        "timestamp": 1728577776443
                    }
                ]
            },
            "lidc": {
                "name": "lidc",
                "domain": ".linkedin.com",
                "path": "/",
                "current_label": 0,
                "label_ts": 1728577775788,
                "storeId": "1",
                "variable_data": [
                    {
                        "host_only": false,
                        "http_only": false,
                        "secure": true,
                        "session": false,
                        "expirationDate": 1728664175.786525,
                        "expiry": 86400.78652501106,
                        "value": "\"b=TGST07:s=T:r=T:a=T:p=T:g=2954:u=1:x=1:i=1728577775:t=1728664175:v=2:sig=AQFn3LyKJlUeUGDTWEGOptxTWjVGHkTy\"",
                        "same_site": "no_restriction",
                        "timestamp": 1728577775788
                    }
                ]
            },
            "bscookie": {
                "name": "bscookie",
                "domain": ".www.linkedin.com",
                "path": "/",
                "current_label": 0,
                "label_ts": 1728577776266,
                "storeId": "1",
                "variable_data": [
                    {
                        "host_only": false,
                        "http_only": true,
                        "secure": true,
                        "session": false,
                        "expirationDate": 1760113777.265357,
                        "expiry": 31536001.265357018,
                        "value": "\"v=1&20241010162936eef791ad-21f6-4901-8a29-19c7775a3a82AQEuA22527CD6eGOs4iV56Mc7_zRHi4S\"",
                        "same_site": "no_restriction",
                        "timestamp": 1728577776266
                    }
                ]
            }
        }
    },
    "radio-canada.ca": {
        "/": {
            "AKA_A2": {
                "name": "AKA_A2",
                "domain": ".radio-canada.ca",
                "path": "/",
                "current_label": 0,
                "label_ts": 1728577760663,
                "storeId": "1",
                "variable_data": [
                    {
                        "host_only": false,
                        "http_only": true,
                        "secure": true,
                        "session": false,
                        "expirationDate": 1728581360.657855,
                        "expiry": 3600.6578550338745,
                        "value": "A",
                        "same_site": "unspecified",
                        "timestamp": 1728577760660
                    }
                ]
            },
            "AMCVS_55E654E45894AF350A495CFE%40AdobeOrg": {
                "name": "AMCVS_55E654E45894AF350A495CFE%40AdobeOrg",
                "domain": ".radio-canada.ca",
                "path": "/",
                "current_label": 3,
                "label_ts": 1728577763254,
                "storeId": "1",
                "variable_data": [
                    {
                        "host_only": false,
                        "http_only": false,
                        "secure": false,
                        "session": true,
                        "expiry": 0,
                        "value": "1",
                        "same_site": "unspecified",
                        "timestamp": 1728577763254
                    }
                ]
            },
            "AMCV_55E654E45894AF350A495CFE%40AdobeOrg": {
                "name": "AMCV_55E654E45894AF350A495CFE%40AdobeOrg",
                "domain": ".radio-canada.ca",
                "path": "/",
                "current_label": 3,
                "label_ts": 1728577762488,
                "storeId": "1",
                "variable_data": [
                    {
                        "host_only": false,
                        "http_only": false,
                        "secure": false,
                        "session": false,
                        "expirationDate": 1763137762.487152,
                        "expiry": 34560000.4871521,
                        "value": "T",
                        "same_site": "unspecified",
                        "timestamp": 1728577762487
                    },
                    {
                        "host_only": false,
                        "http_only": false,
                        "secure": false,
                        "session": false,
                        "expiry": 34560000.4876709,
                        "value": "1406116232%7CMCIDTS%7C20007%7CvVersion%7C2.5.0",
                        "same_site": "unspecified",
                        "timestamp": 1728577762488
                    },
                    {
                        "host_only": false,
                        "http_only": false,
                        "secure": false,
                        "session": false,
                        "expiry": 34560000.25002599,
                        "value": "1406116232%7CMCIDTS%7C20007%7CMCMID%7C89187083084297400563729106907981953874%7CvVersion%7C2.5.0",
                        "same_site": "unspecified",
                        "timestamp": 1728577763251
                    },
                    {
                        "host_only": false,
                        "http_only": false,
                        "secure": false,
                        "session": false,
                        "expiry": 34560000.25087404,
                        "value": "1406116232%7CMCIDTS%7C20007%7CMCMID%7C89187083084297400563729106907981953874%7CMCAAMLH-1729182563%7C7%7CMCAAMB-1729182563%7C6G1ynYcLPuiQxYZrsz_pkqfLG9yMXBpb2zX5dvJdYQJzPXImdj0y%7CvVersion%7C2.5.0",
                        "same_site": "unspecified",
                        "timestamp": 1728577763252
                    },
                    {
                        "host_only": false,
                        "http_only": false,
                        "secure": false,
                        "session": false,
                        "expiry": 34560000.25298691,
                        "value": "1406116232%7CMCIDTS%7C20007%7CMCMID%7C89187083084297400563729106907981953874%7CMCAAMLH-1729182563%7C7%7CMCAAMB-1729182563%7C6G1ynYcLPuiQxYZrsz_pkqfLG9yMXBpb2zX5dvJdYQJzPXImdj0y%7CMCOPTOUT-1728584963s%7CNONE%7CvVersion%7C2.5.0",
                        "same_site": "unspecified",
                        "timestamp": 1728577763255
                    },
                    {
                        "host_only": false,
                        "http_only": false,
                        "secure": false,
                        "session": false,
                        "expiry": 34560000.04535198,
                        "value": "1406116232%7CMCIDTS%7C20007%7CMCMID%7C89187083084297400563729106907981953874%7CMCAAMLH-1729182563%7C7%7CMCAAMB-1729182563%7C6G1ynYcLPuiQxYZrsz_pkqfLG9yMXBpb2zX5dvJdYQJzPXImdj0y%7CMCOPTOUT-1728584963s%7CNONE%7CMCAID%7CNONE%7CvVersion%7C2.5.0",
                        "same_site": "unspecified",
                        "timestamp": 1728577764046
                    },
                    {
                        "host_only": false,
                        "http_only": false,
                        "secure": false,
                        "session": false,
                        "expiry": 34560000.08990502,
                        "value": "1406116232%7CMCIDTS%7C20007%7CMCMID%7C89187083084297400563729106907981953874%7CMCAAMLH-1729182563%7C7%7CMCAAMB-1729182563%7C6G1ynYcLPuiQxYZrsz_pkqfLG9yMXBpb2zX5dvJdYQJzPXImdj0y%7CMCOPTOUT-1728584963s%7CNONE%7CMCAID%7CNONE%7CMCSYNCSOP%7C411-20014%7CvVersion%7C2.5.0",
                        "same_site": "unspecified",
                        "timestamp": 1728577764091
                    },
                    {
                        "host_only": false,
                        "http_only": false,
                        "secure": false,
                        "session": false,
                        "expiry": 34560000.372669935,
                        "value": "-1303530583%7CMCIDTS%7C20007%7CMCMID%7C89187083084297400563729106907981953874%7CMCAAMLH-1729182574%7C7%7CMCAAMB-1728577714.229%7C6G1ynYcLPuiQxYZrsz_pkqfLG9yMXBpb2zX5dvJdYQJzPXImdj0y%7CMCOPTOUT-1728577714.229s%7CNONE%7CMCAID%7CNONE%7CMCSYNCSOP%7C411-20014%7CvVersion%7C3.3.0",
                        "same_site": "unspecified",
                        "timestamp": 1728577774373
                    },
                    {
                        "host_only": false,
                        "http_only": false,
                        "secure": false,
                        "session": false,
                        "expiry": 34560000.374752045,
                        "value": "-1303530583%7CMCIDTS%7C20007%7CMCMID%7C89187083084297400563729106907981953874%7CMCAAMLH-1729182574%7C7%7CMCAAMB-1729182574%7C6G1ynYcLPuiQxYZrsz_pkqfLG9yMXBpb2zX5dvJdYQJzPXImdj0y%7CMCOPTOUT-1728584974s%7CNONE%7CMCAID%7CNONE%7CMCSYNCSOP%7C411-20014%7CvVersion%7C3.3.0",
                        "same_site": "unspecified",
                        "timestamp": 1728577774378
                    }
                ]
            },
            "RC_CDM_REGION": {
                "name": "RC_CDM_REGION",
                "domain": ".radio-canada.ca",
                "path": "/",
                "current_label": 0,
                "label_ts": 1728577760669,
                "storeId": "1",
                "variable_data": [
                    {
                        "host_only": false,
                        "http_only": false,
                        "secure": false,
                        "session": false,
                        "expirationDate": 1760113760.660033,
                        "expiry": 31536000.660032988,
                        "value": "27",
                        "same_site": "unspecified",
                        "timestamp": 1728577760669
                    }
                ]
            },
            "RC_CDM_REGION_OHDIO": {
                "name": "RC_CDM_REGION_OHDIO",
                "domain": ".radio-canada.ca",
                "path": "/",
                "current_label": 0,
                "label_ts": 1728577760668,
                "storeId": "1",
                "variable_data": [
                    {
                        "host_only": false,
                        "http_only": false,
                        "secure": false,
                        "session": false,
                        "expirationDate": 1760113760.659923,
                        "expiry": 31536000.659923077,
                        "value": "27",
                        "same_site": "unspecified",
                        "timestamp": 1728577760666
                    }
                ]
            },
            "RC_CDM_REGION_TELE": {
                "name": "RC_CDM_REGION_TELE",
                "domain": ".radio-canada.ca",
                "path": "/",
                "current_label": 3,
                "label_ts": 1728577760669,
                "storeId": "1",
                "variable_data": [
                    {
                        "host_only": false,
                        "http_only": false,
                        "secure": false,
                        "session": false,
                        "expirationDate": 1760113760.659999,
                        "expiry": 31536000.659998894,
                        "value": "11",
                        "same_site": "unspecified",
                        "timestamp": 1728577760668
                    }
                ]
            },
            "_fbp": {
                "name": "_fbp",
                "domain": ".radio-canada.ca",
                "path": "/",
                "current_label": 3,
                "label_ts": 1728577763515,
                "storeId": "1",
                "variable_data": [
                    {
                        "host_only": false,
                        "http_only": false,
                        "secure": false,
                        "session": false,
                        "expirationDate": 1736353763,
                        "expiry": 7776000,
                        "value": "fb.1.1728577763514.439655444180449478",
                        "same_site": "lax",
                        "timestamp": 1728577763515
                    },
                    {
                        "host_only": false,
                        "http_only": false,
                        "secure": false,
                        "session": false,
                        "expiry": 7776000,
                        "value": "fb.1.1728577763514.439655444180449478",
                        "same_site": "lax",
                        "timestamp": 1728577771866
                    },
                    {
                        "host_only": false,
                        "http_only": false,
                        "secure": false,
                        "session": false,
                        "expiry": 7776000,
                        "value": "fb.1.1728577763514.439655444180449478",
                        "same_site": "lax",
                        "timestamp": 1728577775603
                    }
                ]
            },
            "_ga": {
                "name": "_ga",
                "domain": ".radio-canada.ca",
                "path": "/",
                "current_label": 2,
                "label_ts": 1728577774907,
                "storeId": "1",
                "variable_data": [
                    {
                        "host_only": false,
                        "http_only": false,
                        "secure": false,
                        "session": false,
                        "expirationDate": 1763137774.904797,
                        "expiry": 34560000.90479708,
                        "value": "GA1.1.1668571109.1728577775",
                        "same_site": "unspecified",
                        "timestamp": 1728577774906
                    },
                    {
                        "host_only": false,
                        "http_only": false,
                        "secure": false,
                        "session": false,
                        "expiry": 34560000.2164669,
                        "value": "GA1.2.1668571109.1728577775",
                        "same_site": "unspecified",
                        "timestamp": 1728577776217
                    }
                ]
            },
            "_ga_Z0D7EXK8C8": {
                "name": "_ga_Z0D7EXK8C8",
                "domain": ".radio-canada.ca",
                "path": "/",
                "current_label": 2,
                "label_ts": 1728577774906,
                "storeId": "1",
                "variable_data": [
                    {
                        "host_only": false,
                        "http_only": false,
                        "secure": false,
                        "session": false,
                        "expirationDate": 1763137774.904561,
                        "expiry": 34560000.90456104,
                        "value": "GS1.1.1728577774.1.0.1728577774.60.0.0",
                        "same_site": "unspecified",
                        "timestamp": 1728577774905
                    },
                    {
                        "host_only": false,
                        "http_only": false,
                        "secure": false,
                        "session": false,
                        "expiry": 34560000.90959501,
                        "value": "deleted",
                        "same_site": "unspecified",
                        "timestamp": 1728577774910
                    },
                    {
                        "host_only": false,
                        "http_only": false,
                        "secure": false,
                        "session": false,
                        "expiry": 34560000.910145044,
                        "value": "GS1.1.1728577774.1.0.1728577774.60.0.0",
                        "same_site": "unspecified",
                        "timestamp": 1728577774910
                    },
                    {
                        "host_only": false,
                        "http_only": false,
                        "secure": false,
                        "session": false,
                        "expiry": 34560000.15091205,
                        "value": "deleted",
                        "same_site": "unspecified",
                        "timestamp": 1728577780151
                    },
                    {
                        "host_only": false,
                        "http_only": false,
                        "secure": false,
                        "session": false,
                        "expiry": 34560000.15134597,
                        "value": "GS1.1.1728577774.1.0.1728577780.54.0.0",
                        "same_site": "unspecified",
                        "timestamp": 1728577780152
                    }
                ]
            },
            "_gat_gtag_UA_398145_19": {
                "name": "_gat_gtag_UA_398145_19",
                "domain": ".radio-canada.ca",
                "path": "/",
                "current_label": 2,
                "label_ts": 1728577776221,
                "storeId": "1",
                "variable_data": [
                    {
                        "host_only": false,
                        "http_only": false,
                        "secure": false,
                        "session": false,
                        "expirationDate": 1728577836,
                        "expiry": 60,
                        "value": "1",
                        "same_site": "unspecified",
                        "timestamp": 1728577776220
                    }
                ]
            },
            "_gcl_au": {
                "name": "_gcl_au",
                "domain": ".radio-canada.ca",
                "path": "/",
                "current_label": 3,
                "label_ts": 1728577762638,
                "storeId": "1",
                "variable_data": [
                    {
                        "host_only": false,
                        "http_only": false,
                        "secure": false,
                        "session": false,
                        "expirationDate": 1736353762,
                        "expiry": 7776000,
                        "value": "1.1.1926097434.1728577763",
                        "same_site": "unspecified",
                        "timestamp": 1728577762637
                    },
                    {
                        "host_only": false,
                        "http_only": false,
                        "secure": false,
                        "session": false,
                        "expiry": 7776001,
                        "value": "1.1.1926097434.1728577763",
                        "same_site": "unspecified",
                        "timestamp": 1728577762926
                    },
                    {
                        "host_only": false,
                        "http_only": false,
                        "secure": false,
                        "session": false,
                        "expiry": 7776000,
                        "value": "1.1.1926097434.1728577763",
                        "same_site": "unspecified",
                        "timestamp": 1728577763026
                    },
                    {
                        "host_only": false,
                        "http_only": false,
                        "secure": false,
                        "session": false,
                        "expiry": 7776000,
                        "value": "1.1.1926097434.1728577763",
                        "same_site": "unspecified",
                        "timestamp": 1728577763054
                    },
                    {
                        "host_only": false,
                        "http_only": false,
                        "secure": false,
                        "session": false,
                        "expiry": 7776000,
                        "value": "1.1.1926097434.1728577763",
                        "same_site": "unspecified",
                        "timestamp": 1728577763072
                    }
                ]
            },
            "_gid": {
                "name": "_gid",
                "domain": ".radio-canada.ca",
                "path": "/",
                "current_label": 2,
                "label_ts": 1728577776219,
                "storeId": "1",
                "variable_data": [
                    {
                        "host_only": false,
                        "http_only": false,
                        "secure": false,
                        "session": false,
                        "expirationDate": 1728664176,
                        "expiry": 86400,
                        "value": "GA1.2.1539823600.1728577776",
                        "same_site": "unspecified",
                        "timestamp": 1728577776218
                    }
                ]
            },
            "ak_bmsc": {
                "name": "ak_bmsc",
                "domain": ".radio-canada.ca",
                "path": "/",
                "current_label": 0,
                "label_ts": 1728577760671,
                "storeId": "1",
                "variable_data": [
                    {
                        "host_only": false,
                        "http_only": false,
                        "secure": false,
                        "session": false,
                        "expiry": 7198.839831113815,
                        "value": "09E7E67E0BDD8710F3C3D106C86AC3B6~000000000000000000000000000000~YAAQJJYqF21mgHKSAQAAG3NDdxnPr9v1wnupKiBiBwPXD7dLQiewIv38cDUNid46xieGfVye/6113UAKKqIQB7K/Vd7YIr6nDOzgfVKoJwOyXedQ00rKEuYhtXPxUz6EtKv4rUfkd79HSs1aaRSZeNoGwCIBRb5XM6nJlucmI9N1CqrNY7yPLcCkbxHWrzepsZZIAZlBSH7IcyeqvTn6b+ytKX/YsUYU6NIHmmd0bAU3nHIHswNuz1x8e7jEbpEI8j3ozX1kHD0WE47ZlccRbkYJExtCr9h+m0dzu+U8rN4hmWBkj3F3StNwVRGP1GA63ruJ9MGtKXpWo80kbOQu3ZTT2ppsGqcAHCfOTJkbqXWnribK+jA5HNxOuINUu2NizzBOf5U8KnhuipHAw/IXgvdE7SyKN+4nbft5GZCcpA2NxwBuib+WPDVpqmnKN+oHNQsmwwY=",
                        "same_site": "unspecified",
                        "timestamp": 1728577761840
                    },
                    {
                        "host_only": false,
                        "http_only": false,
                        "secure": false,
                        "session": false,
                        "expiry": 7198.850663900375,
                        "value": "09E7E67E0BDD8710F3C3D106C86AC3B6~000000000000000000000000000000~YAAQJJYqF2tmgHKSAQAAGnNDdxk2HHdxmauUKhn0esvIfC0dNEfwb4V+dBlpETTcgwsA9LPxezrJsQycqOF6Psrw7zHBFKcLuMIIv8UYBMtXTqzvskrbPg9FiUoWzjnAFOH+r1oYJZBy7v8wUl2zWw6zCCIITUUIYTeMChqOJFe6QErcs+2n/lsB/CEREcZ0Z0T4KmVxFvAgKkCDUuTAmveIQFzl23J9ZjV0T2dOXN6TH1e0rT4ip9fdAbYg1gk2l/c9O7lZ7i2dSSVf6UcHKyDYaJjlqJFq0J1Tq4CXjttEF7heWt8Ceaj7Z5yO8aR/bXwezb6Ww/Zo4qYafqiAYh+e9aVwb2cy/lHH4uFCUPhP095BzLtOmldN1jFjJ91i2Ia08IDhOx/sX8VZjF7E3A7XLwMNQBl/UpJCKFz0sur8dlIVdDD2E4/oeC38k9/dJ3PMJm8=",
                        "same_site": "unspecified",
                        "timestamp": 1728577761851
                    },
                    {
                        "host_only": false,
                        "http_only": false,
                        "secure": false,
                        "session": false,
                        "expiry": 7198.851440906525,
                        "value": "09E7E67E0BDD8710F3C3D106C86AC3B6~000000000000000000000000000000~YAAQJJYqF29mgHKSAQAAHXNDdxlb2j03yEyO0aaRuAlqvqgVg3Js9iB1xYnAWywqcx2jRqpF0yQc/7m1iLi5H26+vT794acTLyIl2mTUX//+Pr4uSxk+Pe5/oNkA1XS/upeFzNHrs5T9OcANKrxx3maRPxycXpFLIr088hKCXyoOJU7vIUOQVZ85JM8tms1klUsywKjltM2JOx6Vx41azCOpFarsckkB9Fou8ixGU94IaB9NTqkdOuetcAvs5lFqQNsLVCNnZpi/esk4YTj8EsOgFfThN6Lo/iZReNsAOsUmKqgNx7mlL+VE4zUadcMwVeyu2BBCDtc6zfwupcloPyBIlQ3WdagVC7ZhPWTi+ke6K0KwQm+KqIIf3lIAlfCDtBQdsxWYGQScNVGe2HZGBdPpaskejCP0Ph4imlShc05Yo2XOCJ+NmlJzRPWvmgtwDo1FZkU=",
                        "same_site": "unspecified",
                        "timestamp": 1728577761852
                    },
                    {
                        "host_only": false,
                        "http_only": false,
                        "secure": false,
                        "session": false,
                        "expiry": 7198.865557909012,
                        "value": "09E7E67E0BDD8710F3C3D106C86AC3B6~000000000000000000000000000000~YAAQJJYqF3ZmgHKSAQAAJnNDdxlB+ccNayus1aZi8tlnQAI/8rLGO+kI9fNM2uvr4IlqzC61ly7w+damz/zDJFXrivvya9DmdZdnxqYtweSgHeKlntfwUHkCyyGgvBvxkG2JuIZDT9qDaA0EE+0m6jBHvjWSjGipZNViDKjQPfQgt2TRCZ08spVksQN2c2CqvrYd27rzBuFpRnE7U12IA5SzFxT6CYMU583bhXLTzf16eNriptCiEmv1dJ9mPjncbJSlx+EATuqo5Lh/7M/MElTuD8DvNy7DqeJ2GCr8Znw2miZewbnlxFCdwVOf7xwAN2hiXH5EgrAzjm7woRc0tVkVnq+W34JZtOVddMcra4XoDgq+8AcU7K2GT8P+ow7mIKj3mayp5JDbaDkyiPl7YjlFBNF3L7HvUZi3JIiDfL527vx6PtOJjG489Ym3bi8N4gteoH4=",
                        "same_site": "unspecified",
                        "timestamp": 1728577761866
                    },
                    {
                        "host_only": false,
                        "http_only": false,
                        "secure": false,
                        "session": false,
                        "expiry": 7198.867305994034,
                        "value": "09E7E67E0BDD8710F3C3D106C86AC3B6~000000000000000000000000000000~YAAQJJYqF3tmgHKSAQAANHNDdxlkE2IOrDuxmY2lMFuW+qHTCD6GXLATdrb1Duh7NA5bd3jGIvxEcGHtoDzo7SiATyHPiy/TLk/yDKgVhI5Z6AaXWx9A6PvaoJjrg6TTKHUl0hzlwyX472yPl+Btc6D/1x0yGmxwy2DnF+FedzJXZxcM2KO1k9vrFwOV9S5Yg6j3qqzZCIJUHOaUXTN+zJdd61bY1WzF8kR3d0coKrrp//cXyOL8bGhihHXkNHS5Tmqrr6QXGfDWG5JPm6iXQy0WOIhBir0xr1pGocVn8IGTT/Zk2JHFBRoKJTswCKUjdeLFWJi0+oO9+KDcEMMCxa7Ntg5i/yr08yq09IEEfFIXO+39bxNB6FhP+nCXvNCw2mpVQWzoO54rTS8I59jSeVzrMorUx14oSdarJN5LL3Yhzs6A2jsSlMx/EakHgNtB8O/JFQU=",
                        "same_site": "unspecified",
                        "timestamp": 1728577761867
                    },
                    {
                        "host_only": false,
                        "http_only": false,
                        "secure": false,
                        "session": false,
                        "expiry": 7198.874449014664,
                        "value": "09E7E67E0BDD8710F3C3D106C86AC3B6~000000000000000000000000000000~YAAQJJYqF35mgHKSAQAAPnNDdxmivv6CcIPDJfVLI7u8TkTekwOqPNCmWJngCgzKX09W/mdWTM9ly1g6KSSjSjaiZp6bG/kxkkeECSo+URw5x7KyA5zFKWKxOe5KKckKSWvf3eIKVA3dXOjU+h3Sl8ZWnBrXjfy+j+l+LfYgHqduspN36blldi8c0d91xNrrpZN0DjtmIsOVNxdit46R2riUSCqtVBtMhoiRulDwxCw13XyvhdSokzEZNC+ZEQLQJP0EIed/eRm9nV1T7PgrdJFoyxSNd5H2XzjaD+Skr6N67phufT4J1sMWtwWAB0jrILzEVGZrgukGuMV43hFJA17Vbm29B7x6Ut2R+1+VxZmGVfcxcDnFkPAtWuvS5YfBffD4Q2C4q6rMlKInOqjWzC9Qs68BrG0q6MtYF8FxQ8FRpWy8pbUOxiT3WRvUxz9h4RtVMEE=",
                        "same_site": "unspecified",
                        "timestamp": 1728577761874
                    },
                    {
                        "host_only": false,
                        "http_only": false,
                        "secure": false,
                        "session": false,
                        "expiry": 7198.877989053726,
                        "value": "09E7E67E0BDD8710F3C3D106C86AC3B6~000000000000000000000000000000~YAAQJJYqF4BmgHKSAQAAQnNDdxkar6wnTtetEB7Oq1qCDwEQgHN8eqM1hcDSChlWN29PnfuYpq9zpWBx3apSrESVaCs0HmgW0iDryACDq+E/ZbwVrsVwwZ0yWMnKQHaXwTXmxKKeIRNdEzyBfL/co6Hvf9ju7JVguML8pknky1enmd7zxgsrEgZ/JIZjOLR/eQVCE/bSp3mDUDfTh/eJ3k0rO40Vn/XrSy9nQf/nO7USNLMZUBMYeBMLs+258e+yN44cD8lQa5TE70aBUcmb03R6KKRp3sfEHJHFD9pm4KpVRFXni1kBALQJiEldJX5rpi3ZYnRFTxaO9uzMNjLaobysdcsKWoQSGCwT9aJ8atrTu4IMQtsgFIFkF0PoiE7YYz+7IkDHVSeM5KbTyfjZG8DDLJWzOQ6n0H0UVVe9Gro/0/C4157FvPAmEQwukqB1tRSKqKM=",
                        "same_site": "unspecified",
                        "timestamp": 1728577761878
                    },
                    {
                        "host_only": false,
                        "http_only": false,
                        "secure": false,
                        "session": false,
                        "expiry": 7198.893484115601,
                        "value": "09E7E67E0BDD8710F3C3D106C86AC3B6~000000000000000000000000000000~YAAQJJYqF4ZmgHKSAQAAUHNDdxmhu4oKiw8Dnhwo8/QuJQJt5iKWCKua1x7CZr4phOeAONxPpATaJnwkAivIjyLMH8K19bYh+B6EdC3ctQ/qdk2P6PHjy/ssmR+A41u4CnvrgGlB8Vwqm0hS9mynlMcPcZHV9W9f+rsvueguyt730rEWrQ6zjVVNEPBf44oVCJpwkahuhBTguQlSgrbJmLqQY22KfvnL6dVoFeCdSBOtzRPVrmLUEMGX8Y8jatGbU5A38vBcWXhylgO1KEIV2P8DD53qYXDcWtBXun+Wey299CyCYyprIDsdEnWwHYwbGAjSnO4yOTA8zoQpdslvj8PrIynfdAZ8dT78Q2XOtnBvbyhhXSoNDoIvRx2X4hwcLfyji/UMqoXPjhYeKxEd4JrzMwlSwwbsfpZaknE77zzqA1c+4T161+gzU5NNjlnsyjAmptk=",
                        "same_site": "unspecified",
                        "timestamp": 1728577761894
                    },
                    {
                        "host_only": false,
                        "http_only": false,
                        "secure": false,
                        "session": false,
                        "expiry": 7198.931529045105,
                        "value": "09E7E67E0BDD8710F3C3D106C86AC3B6~000000000000000000000000000000~YAAQJJYqF5ZmgHKSAQAAd3NDdxk3racDoryh/Uzt0fyyNpS4emuVLPaigsezQAvWhNpfgK7sULr/BPwah6oHi8RTFXYdmW5/+BY8fXaIf38MMwv1PB3Fz0TcrJGRTx/6Qgb/GFMEMnEaJyOEYHFCHoh7f3C9PLjWcyh+5rTpyqCMDxTD3BN85S8FvQTnP6b0BByNVRmQSwGEN8aF22LcMYvxZZGBr2U8QPmYGPCnPnZ4bZ48ipGR1SLqI1VBzJjKLUNK/FDaoFU5Bbkk9N6pbtxOtKtR9IMRZW/4rEi3ScIFboMDD7VW/BDsVo5tvBQgjrluYbO9/jfrbEKMgKlah3xMfQdBOChB9XcZnBK9YvqaEXY9RIo6FU5Cumwtcq5SHyySI8tHsc0CzpcyO1BxgzrZO0FJNIYMAO0F0qhbnS5gKNs8UEw+/JLNSPwTH/aF2YxfmIM=",
                        "same_site": "unspecified",
                        "timestamp": 1728577761932
                    },
                    {
                        "host_only": false,
                        "http_only": false,
                        "secure": false,
                        "session": false,
                        "expiry": 7198.4421401023865,
                        "value": "09E7E67E0BDD8710F3C3D106C86AC3B6~000000000000000000000000000000~YAAQJJYqFzhngHKSAQAAdnVDdxmzM7BQ7Yli6XjTkrOG+ScxwJb2lHcRQzXg27SPsTQPqLMOpeIyyQEmY1+r5QsKnK7FBl+5We0W7yuFLLXuKBBVkWe6HZ8sYfaX8ykqVFiumgwUC/9TEC+uMvbcAXPM3r/w0X5L4ypm7Nq6i/BlhCAARuMIvFxvATuNNX2oyWvMlt5mX04/pNbIMQ1Sw9d9Npoe8uARTFTbV7/0f1ORoMRFe0QR8DJURO2m5DBWS9X2u6KuvZsdLkBxA2j3sIL8anHyxz7GSAJyRQyXGv0IFJL+XhdCRzf9C0Mz5ysR/2EcIb6FOFnwgBSDGLIihJ7vip6nDSUGZRGTp3iVj2R4eAbPXUPFz8mG6jXQ1fwD8NPgykCv+zmJCXzkcrp8ewmSrOgUYRyTX9NtsY9XycjWU7FfWKKHKqyVTGlbKhi0XmqHL641VAxssOwH8sOe5Io=",
                        "same_site": "unspecified",
                        "timestamp": 1728577762442
                    }
                ]
            },
            "bm_sv": {
                "name": "bm_sv",
                "domain": ".radio-canada.ca",
                "path": "/",
                "current_label": 0,
                "label_ts": 1728577763695,
                "storeId": "1",
                "variable_data": [
                    {
                        "host_only": false,
                        "http_only": false,
                        "secure": true,
                        "session": false,
                        "expirationDate": 1728584963.692776,
                        "expiry": 7200.692775964737,
                        "value": "B05DD5D8564B4F2EA3749E37228D025E~YAAQJJYqF9togHKSAQAAWHpDdxmpRcjb2qqfYFH/b1Elz8Ojqv2k7IN6LTYdXDtpyEutfECrdDcL/FzbfPTfJTN4G/h1ghhGAInnfV51itPQMonpPRs0A302c6FnarCVWkcTyi1w+iD4EUMVEjNC/17bjOPs5xh+mMxuuNjOYfJT/b/0r8ms8cWRU/3Bmdi4OS4GbxjU6TbVDbdLxLuiYM5vwHtW6S40uOfcPRliqnV/+DwuO1q9IsJnJWJafpGyAQeCOA4=~1",
                        "same_site": "unspecified",
                        "timestamp": 1728577763693
                    },
                    {
                        "host_only": false,
                        "http_only": false,
                        "secure": true,
                        "session": false,
                        "expiry": 7196.567962884903,
                        "value": "B05DD5D8564B4F2EA3749E37228D025E~YAAQJJYqF/5tgHKSAQAAUYlDdxm4o0CjeE1UtLpMRHhjb1plybojVdOHI8N266cm5UuGSRcNwGIKI/lU3GJKGkrOj9P7K3ReLhe2R9h/uxfxjG8TOqhgY9CC+IwCVqsjqYJiro7dAoK262qwRQa1jWM6WGNV74LUsibzhAqizAj36A+zp0c3yWBN2Ws4JK93OdryWS2KaXmpFzy5AwlivoBWQFFKQHnBlKGKsxiWrVWOcAztwrLGgSuhg+KMgufP5jc/8xs=~1",
                        "same_site": "unspecified",
                        "timestamp": 1728577767569
                    },
                    {
                        "host_only": false,
                        "http_only": false,
                        "secure": true,
                        "session": false,
                        "expiry": 7191.459461927414,
                        "value": "B05DD5D8564B4F2EA3749E37228D025E~YAAQD5YqF4eX/GySAQAAl5xDdxk2+a8gfZx/8HUJ0TlYeiotP8FqLcVN2DJBbja5SaQryUOtfx5RhlXXq0qyZVynmBllrECAYVdge9Eqc8uwxkIK2g5+H/shcvLmoTFPe0LA9qh/dYxuFOwNUNXeAGKpHioKkb0wcI85SiN90F91Vx2T6J8aVNXuH8fKv6r6FiWKBjGMNWXmUi8YQs3tI89egixqUMZ6bc97bLvJH59imkzMIyp2E1iWtoloyfnPEDEblxY=~1",
                        "same_site": "unspecified",
                        "timestamp": 1728577772462
                    },
                    {
                        "host_only": false,
                        "http_only": false,
                        "secure": true,
                        "session": false,
                        "expiry": 7189.7369821071625,
                        "value": "B05DD5D8564B4F2EA3749E37228D025E~YAAQD5YqF0Sc/GySAQAAdKVDdxkYBoj6etuS/+U27Suz8T7/sVtTjCUbgO8D5uALdiHY6lFMM6LJPThl5Zr5rzRRN+krNn4RbnXTp8Gvlf+3/Cf0GpbrH5ajKmG/3U/L1SMqCghuwNNC3d4bZnUTSBDRWnxkKac/4Z4B6BziZWqCzi5l4zrkk8wO+YRY39u+O9Gkgnf4sin/IU3+tvOfxCJFON1ebf9l4LjP/K+/Jz9YYh1KEe3UOryG7nmcrmGBmGLo9Vc=~1",
                        "same_site": "unspecified",
                        "timestamp": 1728577774737
                    },
                    {
                        "host_only": false,
                        "http_only": false,
                        "secure": true,
                        "session": false,
                        "expiry": 7189.756131887436,
                        "value": "B05DD5D8564B4F2EA3749E37228D025E~YAAQD5YqF0mc/GySAQAAfaVDdxnuYhCIo44vwlVqMt/kbBC87iOInhZANi3VJzm5FqLixsSfvUUNdqb1RP+EfjpnKiSjug6eNawZKigYo1XIL8Z2DYbky1jKwY9od6XjtwoDbRiVHl4r++0euZanLLVT90oEdE0aIazNnjYsjWn3InR/m9hFNyTUtnprEFzwg3BwRzKe5ta+ncKYmmCjwtwFkmNcqH24EAIkIQBLyjIGniW9dG/tyQ9RSfqi3+vaEq9jMJE=~1",
                        "same_site": "unspecified",
                        "timestamp": 1728577774756
                    }
                ]
            },
            "s_cc": {
                "name": "s_cc",
                "domain": ".radio-canada.ca",
                "path": "/",
                "current_label": 2,
                "label_ts": 1728577764048,
                "storeId": "1",
                "variable_data": [
                    {
                        "host_only": false,
                        "http_only": false,
                        "secure": false,
                        "session": true,
                        "expiry": 0,
                        "value": "true",
                        "same_site": "unspecified",
                        "timestamp": 1728577764047
                    },
                    {
                        "host_only": false,
                        "http_only": false,
                        "secure": false,
                        "session": true,
                        "expiry": 0,
                        "value": "true",
                        "same_site": "unspecified",
                        "timestamp": 1728577774795
                    }
                ]
            },
            "s_ecid": {
                "name": "s_ecid",
                "domain": ".radio-canada.ca",
                "path": "/",
                "current_label": 3,
                "label_ts": 1728577764045,
                "storeId": "1",
                "variable_data": [
                    {
                        "host_only": false,
                        "http_only": false,
                        "secure": false,
                        "session": false,
                        "expirationDate": 1763137764.044289,
                        "expiry": 34560000.04428911,
                        "value": "MCMID%7C89187083084297400563729106907981953874",
                        "same_site": "lax",
                        "timestamp": 1728577764044
                    },
                    {
                        "host_only": false,
                        "http_only": false,
                        "secure": false,
                        "session": false,
                        "expiry": 34560000.189431906,
                        "value": "MCMID%7C89187083084297400563729106907981953874",
                        "same_site": "unspecified",
                        "timestamp": 1728577764190
                    }
                ]
            },
            "s_sq": {
                "name": "s_sq",
                "domain": ".radio-canada.ca",
                "path": "/",
                "current_label": 2,
                "label_ts": 1728577771869,
                "storeId": "1",
                "variable_data": [
                    {
                        "host_only": false,
                        "http_only": false,
                        "secure": false,
                        "session": true,
                        "expiry": 0,
                        "value": "rc-prod01%3D%2526c.%2526a.%2526activitymap.%2526page%253Dppage%25253Aaccueil%25253Aaccueil%2526link%253Dplease%252520review%252520your%252520device%252520and%252520browser%252520privacy%252520settings.%252520%252528New%252520window%252529%2526region%253DBODY%2526pageIDType%253D1%2526.activitymap%2526.a%2526.c",
                        "same_site": "unspecified",
                        "timestamp": 1728577771868
                    },
                    {
                        "host_only": false,
                        "http_only": false,
                        "secure": false,
                        "session": true,
                        "expiry": 0,
                        "value": "rc-site-institutionnel-prod%3D%2526c.%2526a.%2526activitymap.%2526page%253Dcbc.radio-canada.ca%25253Afr%25253Atransparence-et-engagement%25253Avie-privee%25253Aavis-de-confidentialite%25253Aoptions-de-confidentialite%25253F_gl%25253D1%25252A1v8ma5e%25252A_gcl_au%25252AMTkyNjA5NzQzNC4xNzI4NTc3NzYz%2526link%253DGoogle%252520Chrome%2526region%253Dmain%2526pageIDType%253D1%2526.activitymap%2526.a%2526.c%2526pid%253Dcbc.radio-canada.ca%25253Afr%25253Atransparence-et-engagement%25253Avie-privee%25253Aavis-de-confidentialite%25253Aoptions-de-confidentialite%25253F_gl%25253D1%25252A1v8ma5e%25252A_gcl_au%25252AMTkyNjA5NzQzNC4xNzI4NTc3NzYz%2526pidt%253D1%2526oid%253Dhttps%25253A%25252F%25252Fsupport.google.com%25252Faccounts%25252Fanswer%25252F61416%25253Fco%25253DGENIE.Platform%2525253DDesktop%252526hl%25253Dfr%2526ot%253DA%26rc-prod01%3D%2526c.%2526a.%2526activitymap.%2526page%253Dppage%25253Aaccueil%25253Aaccueil%2526link%253Dplease%252520review%252520your%252520device%252520and%252520browser%252520privacy%252520settings.%252520%252528New%252520window%252529%2526region%253DBODY%2526pageIDType%253D1%2526.activitymap%2526.a%2526.c",
                        "same_site": "unspecified",
                        "timestamp": 1728577780146
                    }
                ]
            },
            "B4rjGo0j8ltdnU309VVixDENxnaiCZ17dnFtt5Sg": {
                "name": "B4rjGo0j8ltdnU309VVixDENxnaiCZ17dnFtt5Sg",
                "domain": "radio-canada.ca",
                "path": "/",
                "current_label": 0,
                "label_ts": 1728577760081,
                "storeId": "1",
                "variable_data": [
                    {
                        "host_only": true,
                        "http_only": true,
                        "secure": true,
                        "session": false,
                        "expirationDate": 1728584960.048471,
                        "expiry": 7200.0484709739685,
                        "value": "eyJpdiI6IkFVL2d4bC8ycGJCN1Y2WG1YSm1ieFE9PSIsInZhbHVlIjoiWjUxM1k2TksrYVMwTDM5WCsybFRSS2V4VzIreHR4SXhDNjZXdGQzd3VPay9JVXlGaXpBbE10NzZObmkrL0dSNExvakgyb1ZsTmxIVVArWkJzMkgwSFNRTml4QlJ0MXBtUmpwdE5pK2J3NVE4bm1EVEozempHRUFCbThTSlNWdXhsem0xemYxRW9IQ1hRK0ZnSUp4cWZSQ2xQQTE2TGJPSkpFWEl2UnlyZDhHS2dJYnNoSG5rTlNNUUVlVVZDSHZyUEhENitsZml4c21uazhmWlNMSnZoYmVTU1hrWEtnNU9aNUpxUlRQUWRxcHJ3SUJtSnJWWlQ0Rm1oa2ZCWUFLRmdQRHE1OUJOWHRnUE1lOHBxU1grNTBQSlJZUm0yRW9qYWx3YzY2SDlGNE1wV1pkUXhLY3A1MWhUaDNiR1ZnakRteFlaNndSVnNzQW9EZFBhK2Z0UFc0em9ubWxXVnA5OVJ4bjIwdkJzNUJBPSIsIm1hYyI6IjEyZWNmNGZhNmYxYTQwYjI0YTdiMmIxMmU0NGNkZDIwYzY4MjY2MWNmM2E5ZmY2YmFkYzgwYjc2ZTIwM2U3M2MiLCJ0YWciOiIifQ%3D%3D",
                        "same_site": "lax",
                        "timestamp": 1728577760077
                    }
                ]
            },
            "XSRF-TOKEN": {
                "name": "XSRF-TOKEN",
                "domain": "radio-canada.ca",
                "path": "/",
                "current_label": 0,
                "label_ts": 1728577760065,
                "storeId": "1",
                "variable_data": [
                    {
                        "host_only": true,
                        "http_only": false,
                        "secure": true,
                        "session": false,
                        "expirationDate": 1728584960.048189,
                        "expiry": 7200.048188924789,
                        "value": "eyJpdiI6IlFxTWpvUTJsa2xyVWUwcSs4aVZ5NFE9PSIsInZhbHVlIjoicnpoME1HeVZpcm5oZ0ZJUmFWMlFhUUYwQWcwWWEwRWxGMlVuMk1KYzZlaE1uSkM1TDRkcjZXMkJ3TzlhZGpDWlZkRlR1OHNZdUwveTAwU0FpREQ5S0s2cnB1L0VpVzN4czRlaEx4QVFDT1I3MVZyTkxrcXF3QVRja2FRak1VSzIiLCJtYWMiOiJkOTI0MmFjY2NjM2I3MjM4NGFhZWMyYjM4OTRjZjc5NjM2ZmE1NTJjYWYyNWVhZTBjNTg3ZGY4ZDQyMWU5NTBhIiwidGFnIjoiIn0%3D",
                        "same_site": "lax",
                        "timestamp": 1728577760051
                    }
                ]
            },
            "__Host-authentic-web-redirect-session": {
                "name": "__Host-authentic-web-redirect-session",
                "domain": "radio-canada.ca",
                "path": "/",
                "current_label": 0,
                "label_ts": 1728577760077,
                "storeId": "1",
                "variable_data": [
                    {
                        "host_only": true,
                        "http_only": true,
                        "secure": true,
                        "session": false,
                        "expirationDate": 1728584960.048329,
                        "expiry": 7200.048329114914,
                        "value": "eyJpdiI6IkRmd1I0ZWJqV0NkQ3JSTE9DU0ZzdkE9PSIsInZhbHVlIjoidlJxNHE3WVZtWFp2bjhRa3JIbGM2MExMd1E5TTVFVnErTmlRL3YrUzdSVThXT3VJSXFqdVFNSThic2tPcFZqRlZRZFpoVnVHUEJTbkV1K1I2Sm9aYkZFdzJHbEs5TWpXZllqZEhvOWxNWU44bUt5ajR5aXNMdEJFMy9mUVgvUWgiLCJtYWMiOiJmYzg2NGYwZjJiMjcwOWZlNDk1MmJlNzE2NTZhN2VhNGZlY2NjMTUzYWY0MzYyYzExMTJlMTRlZWExYWUxNzY2IiwidGFnIjoiIn0%3D",
                        "same_site": "lax",
                        "timestamp": 1728577760065
                    }
                ]
            }
        }
    },
    "scorecardresearch.com": {
        "/": {
            "UID": {
                "name": "UID",
                "domain": ".scorecardresearch.com",
                "path": "/",
                "current_label": 3,
                "label_ts": 1728577763508,
                "storeId": "1",
                "variable_data": [
                    {
                        "host_only": false,
                        "http_only": false,
                        "secure": true,
                        "session": false,
                        "expirationDate": 1762273763.507439,
                        "expiry": 33696000.5074389,
                        "value": "1450db85033d5d4516aa68b1728577763",
                        "same_site": "no_restriction",
                        "timestamp": 1728577763507
                    },
                    {
                        "host_only": false,
                        "http_only": false,
                        "secure": true,
                        "session": false,
                        "expiry": 33696000.67203212,
                        "value": "1450db85033d5d4516aa68b1728577763",
                        "same_site": "no_restriction",
                        "timestamp": 1728577774673
                    }
                ]
            },
            "XID": {
                "name": "XID",
                "domain": ".scorecardresearch.com",
                "path": "/",
                "current_label": 3,
                "label_ts": 1728577763509,
                "storeId": "1",
                "variable_data": [
                    {
                        "host_only": false,
                        "http_only": false,
                        "secure": true,
                        "session": false,
                        "expirationDate": 1762273763.507563,
                        "expiry": 33696000.507563114,
                        "value": "1450db85033d5d4516aa68b1728577763",
                        "same_site": "no_restriction",
                        "timestamp": 1728577763509
                    },
                    {
                        "host_only": false,
                        "http_only": false,
                        "secure": true,
                        "session": false,
                        "expiry": 33696000.67211294,
                        "value": "1450db85033d5d4516aa68b1728577763",
                        "same_site": "no_restriction",
                        "timestamp": 1728577774673
                    }
                ]
            }
        }
    },
    "support.google.com": {
        "/": {
            "SUPPORT_CONTENT": {
                "name": "SUPPORT_CONTENT",
                "domain": ".support.google.com",
                "path": "/",
                "current_label": 0,
                "label_ts": 1728577781424,
                "storeId": "1",
                "variable_data": [
                    {
                        "host_only": false,
                        "http_only": false,
                        "secure": true,
                        "session": false,
                        "expirationDate": 1728579581.423524,
                        "expiry": 1800.423523902893,
                        "value": "638641745810057576-3751014025",
                        "same_site": "unspecified",
                        "timestamp": 1728577781424
                    }
                ]
            },
            "_ga": {
                "name": "_ga",
                "domain": ".support.google.com",
                "path": "/",
                "current_label": 2,
                "label_ts": 1728577781910,
                "storeId": "1",
                "variable_data": [
                    {
                        "host_only": false,
                        "http_only": false,
                        "secure": false,
                        "session": false,
                        "expirationDate": 1763137781.907505,
                        "expiry": 34560000.907505035,
                        "value": "GA1.1.119363975.1728577782",
                        "same_site": "unspecified",
                        "timestamp": 1728577781910
                    },
                    {
                        "host_only": false,
                        "http_only": false,
                        "secure": false,
                        "session": false,
                        "expiry": 34560000.17866802,
                        "value": "GA1.3.119363975.1728577782",
                        "same_site": "unspecified",
                        "timestamp": 1728577782179
                    }
                ]
            },
            "_ga_H30R9PNQFN": {
                "name": "_ga_H30R9PNQFN",
                "domain": ".support.google.com",
                "path": "/",
                "current_label": 2,
                "label_ts": 1728577781909,
                "storeId": "1",
                "variable_data": [
                    {
                        "host_only": false,
                        "http_only": false,
                        "secure": false,
                        "session": false,
                        "expirationDate": 1763137781.907168,
                        "expiry": 34560000.90716791,
                        "value": "GS1.1.1728577781.1.0.1728577781.0.0.0",
                        "same_site": "unspecified",
                        "timestamp": 1728577781908
                    }
                ]
            },
            "_gat_gtag_UA_175894890_5": {
                "name": "_gat_gtag_UA_175894890_5",
                "domain": ".support.google.com",
                "path": "/",
                "current_label": 2,
                "label_ts": 1728577782183,
                "storeId": "1",
                "variable_data": [
                    {
                        "host_only": false,
                        "http_only": false,
                        "secure": false,
                        "session": false,
                        "expirationDate": 1728577842,
                        "expiry": 60,
                        "value": "1",
                        "same_site": "unspecified",
                        "timestamp": 1728577782182
                    }
                ]
            },
            "_gid": {
                "name": "_gid",
                "domain": ".support.google.com",
                "path": "/",
                "current_label": 2,
                "label_ts": 1728577782181,
                "storeId": "1",
                "variable_data": [
                    {
                        "host_only": false,
                        "http_only": false,
                        "secure": false,
                        "session": false,
                        "expirationDate": 1728664182,
                        "expiry": 86400,
                        "value": "GA1.3.476591213.1728577782",
                        "same_site": "unspecified",
                        "timestamp": 1728577782181
                    }
                ]
            }
        }
    },
    "t.co": {
        "/": {
            "__cf_bm": {
                "name": "__cf_bm",
                "domain": ".t.co",
                "path": "/",
                "current_label": 0,
                "label_ts": 1728577776269,
                "storeId": "1",
                "variable_data": [
                    {
                        "host_only": false,
                        "http_only": true,
                        "secure": true,
                        "session": false,
                        "expirationDate": 1728579576.266239,
                        "expiry": 1800.2662389278412,
                        "value": "JRZFm1OLFZ_tgzCSEDGP.45sQplSbfeuhGfal4R9w34-1728577776-1.0.1.1-tvmX5k5kNt66v6iIrlG50UxCMP0jpBQAQ5aflUVO53wB4DZcRcl_mBFPygVZu9TN3zpPMCQJ.bn1L5aML7pYpw",
                        "same_site": "no_restriction",
                        "timestamp": 1728577776269
                    }
                ]
            },
            "muc_ads": {
                "name": "muc_ads",
                "domain": ".t.co",
                "path": "/",
                "current_label": 3,
                "label_ts": 1728577776269,
                "storeId": "1",
                "variable_data": [
                    {
                        "host_only": false,
                        "http_only": false,
                        "secure": true,
                        "session": false,
                        "expirationDate": 1763137776.266203,
                        "expiry": 34560000.26620293,
                        "value": "6320cff7-f079-42a8-8619-e93376f12340",
                        "same_site": "no_restriction",
                        "timestamp": 1728577776267
                    }
                ]
            }
        }
    },
    "twitter.com": {
        "/": {
            "personalization_id": {
                "name": "personalization_id",
                "domain": ".twitter.com",
                "path": "/",
                "current_label": 0,
                "label_ts": 1728577776332,
                "storeId": "1",
                "variable_data": [
                    {
                        "host_only": false,
                        "http_only": false,
                        "secure": true,
                        "session": false,
                        "expirationDate": 1763137776.331541,
                        "expiry": 34560000.33154106,
                        "value": "\"v1_Audr80Gk80hbJtKfzZr+pA==\"",
                        "same_site": "no_restriction",
                        "timestamp": 1728577776332
                    }
                ]
            }
        }
    },
    "cbc.blueconic.net": {
        "/": {
            "AWSALBCORS": {
                "name": "AWSALBCORS",
                "domain": "cbc.blueconic.net",
                "path": "/",
                "current_label": 0,
                "label_ts": 1728577763757,
                "storeId": "1",
                "variable_data": [
                    {
                        "host_only": true,
                        "http_only": false,
                        "secure": true,
                        "session": false,
                        "expirationDate": 1729182563.754875,
                        "expiry": 604800.7548749447,
                        "value": "q6Uv8KNo4X+v1PpNmrzyWuu3bLLpIAMQFVyjWyFY7TNT97c3opdJBcMGk/NeOk+GPBiOoiWEY1J2mJU0/dlcvdBGeS9EPYztsk6nF8EqRbr2+nz/CU5/Q/6BMXkR",
                        "same_site": "no_restriction",
                        "timestamp": 1728577763755
                    },
                    {
                        "host_only": true,
                        "http_only": false,
                        "secure": true,
                        "session": false,
                        "expiry": 604800.3974480629,
                        "value": "fwKjJnxnkTAUuo5HzTXNFH3LJTDTU8jp/2T6lKsQhYC77XXFk4hRqGenmc3ninOeCdw9S/yV9X2zo3iu3JUFkx9bmbnO34wnFizkbFoq/Emd7iRwQQdovRoGh9j0",
                        "same_site": "no_restriction",
                        "timestamp": 1728577764398
                    }
                ]
            }
        },
        "/DG/DEFAULT": {
            "BCSessionID": {
                "name": "BCSessionID",
                "domain": "cbc.blueconic.net",
                "path": "/DG/DEFAULT",
                "current_label": 0,
                "label_ts": 1728577764399,
                "storeId": "1",
                "variable_data": [
                    {
                        "host_only": true,
                        "http_only": true,
                        "secure": true,
                        "session": false,
                        "expirationDate": 1760113764.397527,
                        "expiry": 31536000.39752698,
                        "value": "f27fd1f1-4baf-463f-a312-1c5bf8cca7b0",
                        "same_site": "no_restriction",
                        "timestamp": 1728577764398
                    }
                ]
            }
        }
    },
    "cbc.radio-canada.ca": {
        "/": {
            "UICulture": {
                "name": "UICulture",
                "domain": "cbc.radio-canada.ca",
                "path": "/",
                "current_label": 0,
                "label_ts": 1728577772462,
                "storeId": "1",
                "variable_data": [
                    {
                        "host_only": true,
                        "http_only": false,
                        "secure": true,
                        "session": false,
                        "expirationDate": 1736353772.45935,
                        "expiry": 7776000.459350109,
                        "value": "c%3Den-CA%7Cuic%3Den-CA",
                        "same_site": "unspecified",
                        "timestamp": 1728577772460
                    }
                ]
            },
            "ai_session": {
                "name": "ai_session",
                "domain": "cbc.radio-canada.ca",
                "path": "/",
                "current_label": 0,
                "label_ts": 1728577776365,
                "storeId": "1",
                "variable_data": [
                    {
                        "host_only": true,
                        "http_only": false,
                        "secure": true,
                        "session": false,
                        "expirationDate": 1728579576.364627,
                        "expiry": 1800.3646268844604,
                        "value": "VhXLbgGe/eHYLdX497Mb91|1728577776364|1728577776364",
                        "same_site": "no_restriction",
                        "timestamp": 1728577776365
                    }
                ]
            },
            "ai_user": {
                "name": "ai_user",
                "domain": "cbc.radio-canada.ca",
                "path": "/",
                "current_label": 2,
                "label_ts": 1728577775315,
                "storeId": "1",
                "variable_data": [
                    {
                        "host_only": true,
                        "http_only": false,
                        "secure": true,
                        "session": false,
                        "expirationDate": 1760113775.313938,
                        "expiry": 31536000.313937902,
                        "value": "YxVj2uP8conSE/rUg3WmGW|2024-10-10T16:29:35.313Z",
                        "same_site": "no_restriction",
                        "timestamp": 1728577775314
                    }
                ]
            }
        }
    },
    "cdp.radio-canada.ca": {
        "/": {
            "AWSALB": {
                "name": "AWSALB",
                "domain": "cdp.radio-canada.ca",
                "path": "/",
                "current_label": 0,
                "label_ts": 1728577763888,
                "storeId": "1",
                "variable_data": [
                    {
                        "host_only": true,
                        "http_only": false,
                        "secure": false,
                        "session": false,
                        "expirationDate": 1729182563.88673,
                        "expiry": 604800.8867299557,
                        "value": "kFwp8qQjZhimgz3wDMvA3N8oPNqikAgCj92FwmM+//AJ9yNrbf1WYD8nBDgrRx506SfOJOb9HGH3NoA6IEblZ9kPHizrrP0oWUYahERwpnvk6vEjop/xztaL/oB1",
                        "same_site": "unspecified",
                        "timestamp": 1728577763887
                    },
                    {
                        "host_only": true,
                        "http_only": false,
                        "secure": false,
                        "session": false,
                        "expiry": 604800.3945200443,
                        "value": "dqQ96T+BNSX8eARo7Z/TUz1QhwLy0AhfQ2rpvdKXwruztdg4KgoXiJGA9sc9kkZQuN7vDJrL/x5896vt6AAupPu6LysvfZIkpnmf0MR2DsUmnqyDN5BXIqAQBxCw",
                        "same_site": "unspecified",
                        "timestamp": 1728577764395
                    },
                    {
                        "host_only": true,
                        "http_only": false,
                        "secure": false,
                        "session": false,
                        "expiry": 604800.3955929279,
                        "value": "IOGZEUljvGiI5WeDUiayw7+Jp6VLZgMgnIhLdtB1q4q6mCWvJvVEfv/rypxZg/pIFcOVfGJaywo4nNtg5LMoWnH2qw5rjM53TcfvCRs09V7pqjkr/MT8D3X1Z3iQ",
                        "same_site": "unspecified",
                        "timestamp": 1728577764397
                    },
                    {
                        "host_only": true,
                        "http_only": false,
                        "secure": false,
                        "session": false,
                        "expiry": 604800.4017720222,
                        "value": "/+WDtrNUNf7B0fKJm6KJXvJDVll0QuVKxSDo5wF2J7mlHPyjjCcJsNjswM3s1/GwgGBMTl6c1KJkJq5JZfMEJnUrmR4xJVFolsS/cw1i0KPz6ZcBrGyMUOAFXhT0",
                        "same_site": "unspecified",
                        "timestamp": 1728577764402
                    }
                ]
            },
            "AWSALBCORS": {
                "name": "AWSALBCORS",
                "domain": "cdp.radio-canada.ca",
                "path": "/",
                "current_label": 0,
                "label_ts": 1728577763889,
                "storeId": "1",
                "variable_data": [
                    {
                        "host_only": true,
                        "http_only": false,
                        "secure": true,
                        "session": false,
                        "expirationDate": 1729182563.886802,
                        "expiry": 604800.8868019581,
                        "value": "kFwp8qQjZhimgz3wDMvA3N8oPNqikAgCj92FwmM+//AJ9yNrbf1WYD8nBDgrRx506SfOJOb9HGH3NoA6IEblZ9kPHizrrP0oWUYahERwpnvk6vEjop/xztaL/oB1",
                        "same_site": "no_restriction",
                        "timestamp": 1728577763889
                    },
                    {
                        "host_only": true,
                        "http_only": false,
                        "secure": true,
                        "session": false,
                        "expiry": 604800.394589901,
                        "value": "dqQ96T+BNSX8eARo7Z/TUz1QhwLy0AhfQ2rpvdKXwruztdg4KgoXiJGA9sc9kkZQuN7vDJrL/x5896vt6AAupPu6LysvfZIkpnmf0MR2DsUmnqyDN5BXIqAQBxCw",
                        "same_site": "no_restriction",
                        "timestamp": 1728577764395
                    },
                    {
                        "host_only": true,
                        "http_only": false,
                        "secure": true,
                        "session": false,
                        "expiry": 604800.3956890106,
                        "value": "IOGZEUljvGiI5WeDUiayw7+Jp6VLZgMgnIhLdtB1q4q6mCWvJvVEfv/rypxZg/pIFcOVfGJaywo4nNtg5LMoWnH2qw5rjM53TcfvCRs09V7pqjkr/MT8D3X1Z3iQ",
                        "same_site": "no_restriction",
                        "timestamp": 1728577764397
                    },
                    {
                        "host_only": true,
                        "http_only": false,
                        "secure": true,
                        "session": false,
                        "expiry": 604800.4018089771,
                        "value": "/+WDtrNUNf7B0fKJm6KJXvJDVll0QuVKxSDo5wF2J7mlHPyjjCcJsNjswM3s1/GwgGBMTl6c1KJkJq5JZfMEJnUrmR4xJVFolsS/cw1i0KPz6ZcBrGyMUOAFXhT0",
                        "same_site": "no_restriction",
                        "timestamp": 1728577764402
                    }
                ]
            }
        },
        "/DG/DEFAULT": {
            "BCSessionID": {
                "name": "BCSessionID",
                "domain": "cdp.radio-canada.ca",
                "path": "/DG/DEFAULT",
                "current_label": 3,
                "label_ts": 1728577764152,
                "storeId": "1",
                "variable_data": [
                    {
                        "host_only": true,
                        "http_only": false,
                        "secure": true,
                        "session": false,
                        "expirationDate": 1763137764.150799,
                        "expiry": 34560000.150799036,
                        "value": "f27fd1f1-4baf-463f-a312-1c5bf8cca7b0",
                        "same_site": "no_restriction",
                        "timestamp": 1728577764151
                    }
                ]
            },
            "BCTempID": {
                "name": "BCTempID",
                "domain": "cdp.radio-canada.ca",
                "path": "/DG/DEFAULT",
                "current_label": 3,
                "label_ts": 1728577763890,
                "storeId": "1",
                "variable_data": [
                    {
                        "host_only": true,
                        "http_only": false,
                        "secure": true,
                        "session": false,
                        "expirationDate": 1728578363.886838,
                        "expiry": 600.8868379592896,
                        "value": "f27fd1f1-4baf-463f-a312-1c5bf8cca7b0",
                        "same_site": "no_restriction",
                        "timestamp": 1728577763889
                    }
                ]
            }
        }
    }
}